[
  {
    "publish_date": "20009-09-09",
    "publisher": "Okari",
    "cover_state": "Good"
  },
  {
    "publish_date": "2020-03-03",
    "publisher": "Jozi",
    "cover_state": "good"
  },
  {
    "publish_date": "2020-09-09",
    "publisher": "Newton",
    "cover_state": "bad"
  },
  {
    "publish_date": "2019-05-05",
    "publisher": "Canbury",
    "cover_state": "bad"
  },
  {
    "publish_date": "2002-09-18",
    "publisher": "Okari",
    "cover_state": "good"
  },
  {
    "publish_date": "2009-09-17",
    "publisher": "Okari Nyandika",
    "cover_state": "good"
  }
]